ecspo/__init__.py
ecspo/channel.py
ecspo/query.py
ecspo/table.py
ecspo-1.0.0.dist-info/LICENSE.txt
ecspo-1.0.0.dist-info/METADATA
ecspo-1.0.0.dist-info/WHEEL
ecspo-1.0.0.dist-info/top_level.txt
ecspo-1.0.0.dist-info/RECORD
