Metadata-Version: 2.1
Name: ecspo
Version: 1.0.0
Summary: A pythonic event driven entity component system
Author-email: Arthur Maul II <arthurmiiengineering@gmail.com>
Project-URL: Homepage, https://github.com/arthurmaul/ECSpo
Project-URL: Issues, https://github.com/arthurmaul/ECSpo/issues
Classifier: Programming Language :: Python :: 3
Classifier: License :: OSI Approved :: MIT License
Classifier: Operating System :: OS Independent
Requires-Python: >=3.8
License-File: LICENSE.txt
